slowo/__init__.py
slowo/emoji.py
slowo/main.py
slowo/nya.py
slowo/stutter.py
slowo/wepwace.py
slowo-0.3.dist-info/LICENSE
slowo-0.3.dist-info/METADATA
slowo-0.3.dist-info/WHEEL
slowo-0.3.dist-info/top_level.txt
slowo-0.3.dist-info/RECORD
