Metadata-Version: 2.1
Name: slowo
Version: 0.3
Summary: A python implentación of advanced uwuification.
Home-page: https://www.github.com/gitautas/slowo
Author: Gintautas Kazlauskas
Author-email: gintautaskazlauskas@protonmail.com
License: GPLv3
Platform: UNKNOWN
License-File: LICENSE
Requires-Dist: wheel
